rmqtools/__init__.py
rmqtools/connection.py
rmqtools/exceptions.py
rmqtools/publisher.py
rmqtools/rmq.py
rmqtools/rpc.py
rmqtools/subscriber.py
rmqtools-1.0.0a4.dist-info/LICENSE
rmqtools-1.0.0a4.dist-info/METADATA
rmqtools-1.0.0a4.dist-info/WHEEL
rmqtools-1.0.0a4.dist-info/top_level.txt
rmqtools-1.0.0a4.dist-info/RECORD
