Metadata-Version: 2.1
Name: rmqtools
Version: 1.0.0a4
Summary: Wrappers for RabbitMQ development in Python. Based on the pika library.
Author-email: Christian Thompson <cjthom43@asu.edu>, Paul Horton <pahorton@asu.edu>
Project-URL: Homepage, https://github.com/217690thompson/rmqtools
Project-URL: Bug Tracker, https://github.com/217690thompson/rmqtools/issues
Classifier: Programming Language :: Python :: 3
Classifier: License :: OSI Approved :: MIT License
Classifier: Operating System :: OS Independent
Requires-Python: >=3.8
License-File: LICENSE
Requires-Dist: pika >=1.3.0
